aprompt/__init__.py
aprompt/_utils.py
aprompt/exceptions.py
aprompt/formatters.py
aprompt/prompts.py
aprompt/py.typed
aprompt/result.py
aprompt/widgets.py
aprompt/ext/argparse/__init__.py
aprompt-3.0.1.dist-info/LICENSE
aprompt-3.0.1.dist-info/METADATA
aprompt-3.0.1.dist-info/WHEEL
aprompt-3.0.1.dist-info/top_level.txt
aprompt-3.0.1.dist-info/RECORD
