Metadata-Version: 2.1
Name: aprompt
Version: 3.0.1
Summary: Advanced Prompts
License: MIT
Project-URL: Documentation, https://aprompt.readthedocs.io/
Project-URL: Source Code, https://github.com/phoenixr-codes/aprompt/
Keywords: form,input,prompt
Classifier: Environment :: Console
Classifier: Intended Audience :: Developers
Classifier: License :: OSI Approved :: MIT License
Classifier: Natural Language :: English
Classifier: Programming Language :: Python :: 3
Classifier: Topic :: Software Development :: User Interfaces
Classifier: Topic :: Software Development
Classifier: Typing :: Typed
Requires-Python: >=3.10
License-File: LICENSE
Requires-Dist: attrs
Requires-Dist: platformdirs
Requires-Dist: readchar
Provides-Extra: dev
Requires-Dist: mypy ; extra == 'dev'
Requires-Dist: pytest ; extra == 'dev'
Provides-Extra: docs
Requires-Dist: furo (>=2022.12.7) ; extra == 'docs'
Requires-Dist: myst-parser (>=1.0) ; extra == 'docs'
Requires-Dist: Sphinx (>=6.1) ; extra == 'docs'
Requires-Dist: sphinx-copybutton (>=0.5) ; extra == 'docs'
